{
  "_fv": 24,
  "_type": "tool",
  "definition": {
    "renderType": 0,
    "texture": "iron_axe",
    "customModelName": "Normal",
    "name": "Oldironaxe",
    "specialInfo": [],
    "creativeTab": {
      "value": "TOOLS"
    },
    "toolType": "Pickaxe",
    "harvestLevel": 1,
    "efficiency": 4.0,
    "attackSpeed": 21.0,
    "enchantability": 4,
    "damageVsEntity": 7.0,
    "usageCount": 120,
    "blocksAffected": [],
    "hasGlow": false,
    "repairItems": [],
    "immuneToFire": false,
    "stayInGridWhenCrafting": false,
    "damageOnCrafting": false
  }
}